{"assets":[{"id":"comp_0","layers":[{"ddd":0,"ind":0,"ty":4,"nm":"列表刷新","ks":{"o":{"k":100},"r":{"k":0},"p":{"k":[13.5,13.5,0]},"a":{"k":[0,0,0]},"s":{"k":[33,33,100]}},"ao":0,"sy":[{"ty":0,"nm":"描边","c":{"k":[0.95,0.54,0.15,1]},"s":{"k":10}}],"shapes":[{"ty":"gr","it":[{"d":2,"ty":"el","s":{"k":[55,55]},"p":{"k":[0,0]},"nm":"椭圆路径 1","mn":"ADBE Vector Shape - Ellipse"},{"ty":"tm","s":{"k":[{"i":{"x":[0.833],"y":[0.833]},"o":{"x":[0.167],"y":[0.167]},"n":["0p833_0p833_0p167_0p167"],"t":0,"s":[10],"e":[80]},{"i":{"x":[0.833],"y":[0.833]},"o":{"x":[0.167],"y":[0.167]},"n":["0p833_0p833_0p167_0p167"],"t":15,"s":[80],"e":[10]},{"i":{"x":[0.833],"y":[0.833]},"o":{"x":[0.167],"y":[0.167]},"n":["0p833_0p833_0p167_0p167"],"t":30,"s":[10],"e":[80]},{"i":{"x":[0.833],"y":[0.833]},"o":{"x":[0.167],"y":[0.167]},"n":["0p833_0p833_0p167_0p167"],"t":45,"s":[80],"e":[10]},{"t":60}],"ix":1},"e":{"k":0,"ix":2},"o":{"k":[{"i":{"x":[0.833],"y":[0.833]},"o":{"x":[0.167],"y":[0.167]},"n":["0p833_0p833_0p167_0p167"],"t":0,"s":[0],"e":[90]},{"i":{"x":[0.833],"y":[0.833]},"o":{"x":[0.167],"y":[0.167]},"n":["0p833_0p833_0p167_0p167"],"t":15,"s":[90],"e":[540]},{"i":{"x":[0.833],"y":[0.833]},"o":{"x":[0.167],"y":[0.167]},"n":["0p833_0p833_0p167_0p167"],"t":30,"s":[540],"e":[630]},{"i":{"x":[0.833],"y":[0.833]},"o":{"x":[0.167],"y":[0.167]},"n":["0p833_0p833_0p167_0p167"],"t":45,"s":[630],"e":[1080]},{"t":60}],"ix":3},"m":1,"ix":2,"nm":"修剪路径 1","mn":"ADBE Vector Filter - Trim"},{"ty":"st","c":{"k":[0.74,0.74,0.74,1]},"o":{"k":100},"w":{"k":10},"lc":2,"lj":2,"nm":"描边 1","mn":"ADBE Vector Graphic - Stroke"},{"ty":"tr","p":{"k":[0,0],"ix":2},"a":{"k":[0,0],"ix":1},"s":{"k":[100,100],"ix":3},"r":{"k":0,"ix":6},"o":{"k":100,"ix":7},"sk":{"k":0,"ix":4},"sa":{"k":0,"ix":5},"nm":"变换"}],"nm":"椭圆 1","np":4,"mn":"ADBE Vector Group"}],"ip":0,"op":68,"st":0,"bm":0,"sr":1}]}],"layers":[{"ddd":0,"ind":0,"ty":0,"nm":"form","refId":"comp_0","ks":{"o":{"k":100},"r":{"k":0},"p":{"k":[13.5,13.5,0]},"a":{"k":[13.5,13.5,0]},"s":{"k":[100,100,100]}},"ao":0,"w":27,"h":27,"ip":0,"op":62,"st":0,"bm":0,"sr":1}],"v":"4.5.4","ddd":0,"ip":0,"op":60,"fr":25,"w":27,"h":27}